bexhoma/__init__.py
bexhoma/__version__.py
bexhoma/clusters.py
bexhoma/collectors.py
bexhoma/configurations.py
bexhoma/evaluators.py
bexhoma/experiments.py
bexhoma/scripts/__init__.py
bexhoma/scripts/experimentsmanager.py
bexhoma/scripts/tpcds.py
bexhoma/scripts/tpch.py
bexhoma-0.8.19.dist-info/licenses/LICENSE
bexhoma-0.8.19.dist-info/METADATA
bexhoma-0.8.19.dist-info/WHEEL
bexhoma-0.8.19.dist-info/entry_points.txt
bexhoma-0.8.19.dist-info/top_level.txt
bexhoma-0.8.19.dist-info/RECORD
