Metadata-Version: 2.4
Name: bexhoma
Version: 0.8.19
Summary: This python tools helps managing DBMS benchmarking experiments in a Kubernetes-based HPC cluster environment. It enables users to configure hardware / software setups for easily repeating tests over varying configurations.
Author-email: "Patrick K. Erdelt" <patrick.erdelt@bht-berlin.de>
License: GNU Affero General Public License v3
Project-URL: Homepage, https://github.com/Beuth-Erdelt/Benchmark-Experiment-Host-Manager
Project-URL: Repository, https://github.com/Beuth-Erdelt/Benchmark-Experiment-Host-Manager
Classifier: Programming Language :: Python :: 3
Classifier: License :: OSI Approved :: GNU Affero General Public License v3
Classifier: Operating System :: OS Independent
Requires-Python: >=3.10.2
License-File: LICENSE
Requires-Dist: urllib3>=2.5.0
Requires-Dist: kubernetes==22.6.0
Requires-Dist: psutil>=5.6.1
Requires-Dist: dbmsbenchmarker>=0.14.16
Requires-Dist: myst_parser
Requires-Dist: HiYaPyCo==0.5.1
Requires-Dist: mistune>=2.0.3
Requires-Dist: numpy>=1.22.2
Requires-Dist: setuptools>=78.1.1
Requires-Dist: Werkzeug>=3.0.6
Requires-Dist: pillow>=10.3.0
Requires-Dist: fonttools>=4.61.0
Requires-Dist: dash>=2.15.0
Requires-Dist: pyarrow>=14.0.2
Requires-Dist: requests>=2.32.4
Requires-Dist: prettytable
Requires-Dist: zipp>=3.19.1
Requires-Dist: seaborn>=0.13.2
Dynamic: license-file
